discord/ext/helpers/__init__.py
discord/ext/helpers/chatbot.py
discord/ext/helpers/database.py
discord/ext/helpers/embed.py
discord/ext/helpers/invite_tracker.py
discord/ext/helpers/paginator.py
discord/ext/helpers/requests.py
discord/ext/helpers/status.py
discord/ext/helpers/webhooks.py
discord_helpers-0.2.0.dist-info/LICENSE.txt
discord_helpers-0.2.0.dist-info/METADATA
discord_helpers-0.2.0.dist-info/WHEEL
discord_helpers-0.2.0.dist-info/top_level.txt
discord_helpers-0.2.0.dist-info/RECORD
