Metadata-Version: 2.1
Name: discord-helpers
Version: 0.2.0
Summary: A helper module for discord.py
Home-page: https://github.com/Dorukyum/discord-helpers
Author: Dorukyum
License: MIT
Project-URL: Source, https://github.com/Dorukyum/discord-helpers
Keywords: discord,discord.py,API
Platform: UNKNOWN
Classifier: Development Status :: 4 - Beta
Classifier: Intended Audience :: Developers
Classifier: Topic :: Software Development :: Build Tools
Classifier: License :: OSI Approved :: MIT License
Classifier: Programming Language :: Python :: 3
License-File: LICENSE.txt
Requires-Dist: aiohttp
Provides-Extra: sqlite
Requires-Dist: aiosqlite ; extra == 'sqlite'
